Workbook
Name back: #REF!

Sheet XLookUp - Q
A1: XLOOKUP 101
A3: Syntax is XLOOKUP(lookup, lookup_array, return_array, [not_found], [match_mode], [search_mode])
A5: Employee | B5: ID | C5: Sales | H5: Sales | I5: Commission
A6: Gary Miller | B6: =_xlfn.XLOOKUP(A6,'XLookUp - Data'!$D$2:$D$33,'XLookUp - Data'!$A$2:$A$33,"Not Found") -> ID4 | C6: =_xlfn.XLOOKUP(A6,'XLookUp - Data'!$D$2:$D$33,'XLookUp - Data'!$B$2:$B$33) -> 216 | H6: 0 | I6: 0.05
A7: James Willard | B7: =_xlfn.XLOOKUP(A7,'XLookUp - Data'!$D$2:$D$33,'XLookUp - Data'!$A$2:$A$33) -> ID18 | C7: =_xlfn.XLOOKUP(A7,'XLookUp - Data'!$D$2:$D$33,'XLookUp - Data'!$B$2:$B$33) -> 369 | H7: 100 | I7: 0.1
A8: Richard Elliot | B8: =_xlfn.XLOOKUP(A8,'XLookUp - Data'!$D$2:$D$33,'XLookUp - Data'!$A$2:$A$33) -> ID12 | C8: =_xlfn.XLOOKUP(A8,'XLookUp - Data'!$D$2:$D$33,'XLookUp - Data'!$B$2:$B$33) -> 337 | H8: 200 | I8: 0.2
A9: Robert Spear | B9: =_xlfn.XLOOKUP(A9,'XLookUp - Data'!$D$2:$D$33,'XLookUp - Data'!$A$2:$A$33) -> ID8 | C9: =_xlfn.XLOOKUP(A9,'XLookUp - Data'!$D$2:$D$33,'XLookUp - Data'!$B$2:$B$33) -> 245
A10: Roger Mun | B10: =_xlfn.XLOOKUP(A10,'XLookUp - Data'!$D$2:$D$33,'XLookUp - Data'!$A$2:$A$33) -> ID20 | C10: =_xlfn.XLOOKUP(A10,'XLookUp - Data'!$D$2:$D$33,'XLookUp - Data'!$B$2:$B$33) -> 390 | H10: Sales | I10: Commission
A11: Paul Garza | B11: =_xlfn.XLOOKUP(A11,'XLookUp - Data'!$D$2:$D$33,'XLookUp - Data'!$A$2:$A$33) -> ID24 | C11: =_xlfn.XLOOKUP(A11,'XLookUp - Data'!$D$2:$D$33,'XLookUp - Data'!$B$2:$B$33) -> 217 | H11: 150
A12: Robert Marquez | B12: =_xlfn.XLOOKUP(A12,'XLookUp - Data'!$D$2:$D$33,'XLookUp - Data'!$A$2:$A$33) -> ID23 | C12: =_xlfn.XLOOKUP(A12,'XLookUp - Data'!$D$2:$D$33,'XLookUp - Data'!$B$2:$B$33) -> 134
A13: Natalie Porter | B13: =_xlfn.XLOOKUP(A13,'XLookUp - Data'!$D$2:$D$33,'XLookUp - Data'!$A$2:$A$33) -> ID3 | C13: =_xlfn.XLOOKUP(A13,'XLookUp - Data'!$D$2:$D$33,'XLookUp - Data'!$B$2:$B$33) -> 111
A14: Kim West | B14: =_xlfn.XLOOKUP(A14,'XLookUp - Data'!$D$2:$D$33,'XLookUp - Data'!$A$2:$A$33) -> ID13 | C14: =_xlfn.XLOOKUP(A14,'XLookUp - Data'!$D$2:$D$33,'XLookUp - Data'!$B$2:$B$33) -> 365
A15: Stevie Bridge | B15: =_xlfn.XLOOKUP(A15,'XLookUp - Data'!$D$2:$D$33,'XLookUp - Data'!$A$2:$A$33) -> ID7 | C15: =_xlfn.XLOOKUP(A15,'XLookUp - Data'!$D$2:$D$33,'XLookUp - Data'!$B$2:$B$33) -> 451

Sheet XLookUp - Data
A2: Employee ID | B2: Sales | C2: Department | D2: Employee
A3: ID18 | B3: 369 | C3: Sales | D3: James Willard
A4: ID8 | B4: 245 | C4: Sales | D4: Robert Spear
A5: ID24 | B5: 217 | C5: Sales | D5: Paul Garza | I5: Employee | J5: ID | K5: Sales
A6: ID23 | B6: 134 | C6: Sales | D6: Robert Marquez | I6: Gary Miller | J6: {=_xlfn.XLOOKUP(I6,$D$2:$D$33,$A$2:$B$33,"Not Found")} -> ID4 | K6: 216
A7: ID13 | B7: 365 | C7: Sales | D7: Kim West | I7: James Willard | J7: {=_xlfn.XLOOKUP(I7,$D$2:$D$33,$A$2:$B$33,"Not Found")} -> ID18 | K7: 369
A8: ID7 | B8: 451 | C8: Sales | D8: Stevie Bridge | I8: Richard Elliot | J8: {=_xlfn.XLOOKUP(I8,$D$2:$D$33,$A$2:$B$33,"Not Found")} -> ID12 | K8: 337
A9: ID19 | B9: 299 | C9: Sales | D9: Paul Wells | I9: Robert Spear | J9: {=_xlfn.XLOOKUP(I9,$D$2:$D$33,$A$2:$B$33,"Not Found")} -> ID8 | K9: 245
A10: ID22 | B10: 412 | C10: Sales | D10: Ewan Thompson | I10: Roger Mun | J10: {=_xlfn.XLOOKUP(I10,$D$2:$D$33,$A$2:$B$33,"Not Found")} -> ID20 | K10: 390
A11: ID5 | B11: 398 | C11: Sales | D11: Walter Miller | I11: Paul Garza | J11: {=_xlfn.XLOOKUP(I11,$D$2:$D$33,$A$2:$B$33,"Not Found")} -> ID24 | K11: 217
A12: ID9 | B12: 133 | C12: Sales | D12: Peter Ramsy | I12: Robert Marquez | J12: {=_xlfn.XLOOKUP(I12,$D$2:$D$33,$A$2:$B$33,"Not Found")} -> ID23 | K12: 134
A13: ID17 | B13: 299 | C13: Sales | D13: Wolfgang Ramjac | I13: Natalie Porter | J13: {=_xlfn.XLOOKUP(I13,$D$2:$D$33,$A$2:$B$33,"Not Found")} -> ID3 | K13: 111
A14: ID10 | B14: 201 | C14: Sales | D14: Brigitte Bond | I14: Kim West | J14: {=_xlfn.XLOOKUP(I14,$D$2:$D$33,$A$2:$B$33,"Not Found")} -> ID13 | K14: 365
A15: ID21 | B15: 236 | C15: Sales | D15: Maria Tot | I15: Stevie Bridge | J15: {=_xlfn.XLOOKUP(I15,$D$2:$D$33,$A$2:$B$33,"Not Found")} -> ID7 | K15: 451
A16: ID3 | B16: 111 | C16: Procurement | D16: Natalie Porter
A17: ID29 | B17: 105 | C17: Procurement | D17: Andre Cooper
A18: ID30 | B18: 114 | C18: Procurement | D18: Robert Musser
A19: ID14 | B19: 483 | C19: Procurement | D19: Ann Withers
A20: ID16 | B20: 129 | C20: Procurement | D20: Corinna Schmidt
A21: ID27 | B21: 344 | C21: Procurement | D21: Mike Saban
A22: ID4 | B22: 216 | C22: Finance | D22: Gary Miller
A23: ID12 | B23: 337 | C23: Finance | D23: Richard Elliot
A24: ID20 | B24: 390 | C24: Finance | D24: Roger Mun
A25: ID28 | B25: 374 | C25: Finance | D25: Daniel Garrett
A26: ID25 | B26: 408 | C26: Finance | D26: Paul Hill
A27: ID1 | B27: 264 | C27: Finance | D27: Crystal Doyle
... A33: ID31 | B33: 132 | C33: Finance | D33: Lukas Hofer

Sheet SEQUENCE
A1: SEQUENCE Function
A3: Syntax of SEQUENCE(rows, [columns], [start], [step])
A5: Basic Demo of Sequence: Generate an index
A14: Every 5 days from today | E14: One letter

Sheet Challenge
A1: Challenge: Create a Quick Overview Report | L1: FALSE
L2: FALSE
A3: 1 | B3: Convert the data to a table. Name the table TableAgent | L3: FALSE
A4: 2 | B4: Create a unique list of sales agents sorted in descending order
A5: 3 | B5: Calculate the total quantity sold by each agent during the entire period | J5: WELL DONE!
A7: Date | B7: Sales Agent | C7: Quantity | E7: Sales Agent | F7: Quantity
A8: 43466 | B8: Stevie Bridge | C8: 5
A9: 43470 | B9: Ewan Thompson | C9: 6
A10: 43474 | B10: Richard Elliot | C10: 1
A11: 43477 | B11: Paul Hill | C11: 9
A12: 43482 | B12: Paul Garza | C12: 2
A13: 43485 | B13: Ewan Thompson | C13: 3
A14: 43490 | B14: Robert Musser | C14: 4
A15: 43492 | B15: Betina Bauer | C15: 9
A16: 43493 | B16: Paul Garza | C16: 10
A17: 43498 | B17: Peter Ramsy | C17: 7
A18: 43501 | B18: Betina Bauer | C18: 10
A19: 43505 | B19: Paul Hill | C19: 8
... A56: 43634 | B56: Paul Garza | C56: 10

Sheet Loan Amortization Table
A1: Dynamic LATs
B3: Input year | C3: 2
B4: Rate | C4: 0.06
B5: Value | C5: 40000
B6: Monthly payment | C6: =-PMT(C4/12,C3*12,C5) -> 1772.8244
B9: Month # | C9: Interest | D9: Principal | E9: Balance

Sheet MAX & MIN IFS
A1: MAX & MIN IFS Function
A4: Division | B4: Region | C4: Revenue | E4: Region
A5: Utility | B5: North America | C5: 44196
A6: Utility | B6: South America | C6: 20898 | E6: Max Revenue for Region
A7: Utility | B7: Asia | C7: 46994
A8: Utility | B8: Europe | C8: 43695 | E8: Min Revenue for Region
A9: Utility | B9: Australia | C9: 34196
A10: Productivity | B10: North America | C10: 34155
A11: Productivity | B11: South America | C11: 24396 | E11: Division
A12: Productivity | B12: Asia | C12: 29276
A13: Productivity | B13: Europe | C13: 45540 | E13: Max Revenue for Division
A14: Productivity | B14: Australia | C14: 29277
A15: Game | B15: North America | C15: 44675 | E15: Min Revenue for Division
A16: Game | B16: South America | C16: 42569
A17: Game | B17: Asia | C17: 43784
A18: Game | B18: Europe | C18: 46336
A19: Game | B19: Australia | C19: 49656

Sheet IFS
A1: IFS Function (Replacement to Nested IFS)
B3: Division | C3: Region | D3: Revenue | E3: Comment | G3: Criteria For Comment | H3: Text to Assign | J3: Traditional IF Formula:
B4: Utility | C4: North America | D4: 44196 | G4: Above 45,000 | H4: Amazing | J4: =IF(Logical Test, Value If True, Value If False)
B5: Utility | C5: South America | D5: 20898 | G5: Above 40,000 | H5: Very Good
B6: Utility | C6: Asia | D6: 46994 | G6: Above 35,000 | H6: Good
B7: Utility | C7: Europe | D7: 43695 | G7: Above 30,000 | H7: Bad
B8: Utility | C8: Australia | D8: 34196 | G8: Equal or Below 30,000 | H8: Very Bad
B9: Productivity | C9: North America | D9: 34155
B10: Productivity | C10: South America | D10: 24396
B11: Productivity | C11: Asia | D11: 29276
B12: Productivity | C12: Europe | D12: 45540
B13: Productivity | C13: Australia | D13: 29277
B14: Game | C14: North America | D14: 44675
B15: Game | C15: South America | D15: 42569
B16: Game | C16: Asia | D16: 43784
B17: Game | C17: Europe | D17: 46336
B18: Game | C18: Australia | D18: 49656

Sheet Combining Text
B2: Example 1 | D2: Concatenate | F2: Concat | H2: Textjoin
B3: This
B4: is
B5: a
B6: sentence
B9: Example 2 | D9: Concatenate | F9: & Formula | H9: Concat | J9: Textjoin
B10: This | C10: I | D10: {=CONCATENATE(B10:B13,C10:C13)} -> ThisI
B11: is | C11: love | D11: islove
B12: a | C12: MS | D12: aMS
B13: sentence | C13: Excel | D13: sentenceExcel
B15: E-mails | F15: TEXTJOIN
B16: MamieH@gnet.com
B17: DebiD@yahoo.com
B18: PalmerA@yahoo.com
B19: ZinaW@gmail.com
B20: SanfordB@hotmail.com
B21: HildeC@gnet.com
B22: PenelopeS@gmail.com
B23: TreasaM@yahoo.com
B24: TameraM@hotmail.com
B25: DonteR@yahoo.com
B26: EvanC@gmail.com
B27: LizetteD@gmail.com
... B35: CleotildeW@hotmail.com

Sheet RANDARRAY
A1: RANDARRAY Function | G1: INDEX
A3: Syntax of RANDARRAY([rows], [columns], [min], [max], [integer])
A5: Random numbers between 0 and 1 | E5: Randomly assign people to teams
E7: Gary Miller | G7: Team 1
E8: James Willard | G8: Team 1
E9: Richard Elliot | G9: Team 1
E10: Robert Spear | G10: Team 1
E11: Roger Mun | G11: Team 2
E12: Paul Garza | G12: Team 2
E13: Robert Marquez | G13: Team 2
A14: Random rounded numbers between 10 and 100 | E14: Natalie Porter | G14: Team 2
E15: Kim West | G15: Team 3
E16: Stevie Bridge | G16: Team 3
E17: Andre Cooper | G17: Team 3
E18: Crystal Doyle | G18: Team 3
E19: Robert Musser | G19: Team 4
E20: Daniel Garrett | G20: Team 4
E21: Ann Withers | G21: Team 4
E22: Paul Hill | G22: Team 4
